crm_eng/__init__.py
crm_eng/gui.py
PocketCRM-0.0.4.dist-info/METADATA
PocketCRM-0.0.4.dist-info/WHEEL
PocketCRM-0.0.4.dist-info/top_level.txt
PocketCRM-0.0.4.dist-info/RECORD
