Metadata-Version: 2.1
Name: PocketCRM
Version: 0.0.4
Summary: A simple CRM library
Home-page: https://github.com/BlackFoxgamingstudio/BDevManager2.git
Author: Russell Powers
Author-email: russell@blackfoxx45.com
Classifier: Programming Language :: Python :: 3
Classifier: License :: OSI Approved :: MIT License
Classifier: Operating System :: OS Independent
Requires-Dist: pandas
Requires-Dist: numpy
Requires-Dist: tk
